MANIFEST.in
README.md
setup.py
eyecatching/ClassyVirtualReferencePoint.py
eyecatching/__init__.py
eyecatching/app.py
eyecatching/camera.py
eyecatching/eyeDetect.py
eyecatching/main.py
eyecatching/readRes.py
eyecatching/requirements.txt
eyecatching/settings.py
eyecatching.egg-info/PKG-INFO
eyecatching.egg-info/SOURCES.txt
eyecatching.egg-info/dependency_links.txt
eyecatching.egg-info/entry_points.txt
eyecatching.egg-info/not-zip-safe
eyecatching.egg-info/requires.txt
eyecatching.egg-info/top_level.txt
eyecatching/haarcascades/haarcascade_eye.xml
eyecatching/haarcascades/haarcascade_eye_tree_eyeglasses.xml
eyecatching/haarcascades/haarcascade_frontalcatface.xml
eyecatching/haarcascades/haarcascade_frontalcatface_extended.xml
eyecatching/haarcascades/haarcascade_frontalface_alt.xml
eyecatching/haarcascades/haarcascade_frontalface_alt2.xml
eyecatching/haarcascades/haarcascade_frontalface_alt_tree.xml
eyecatching/haarcascades/haarcascade_frontalface_default.xml
eyecatching/haarcascades/haarcascade_fullbody.xml
eyecatching/haarcascades/haarcascade_lefteye_2splits.xml
eyecatching/haarcascades/haarcascade_licence_plate_rus_16stages.xml
eyecatching/haarcascades/haarcascade_lowerbody.xml
eyecatching/haarcascades/haarcascade_profileface.xml
eyecatching/haarcascades/haarcascade_righteye_2splits.xml
eyecatching/haarcascades/haarcascade_russian_plate_number.xml
eyecatching/haarcascades/haarcascade_smile.xml
eyecatching/haarcascades/haarcascade_upperbody.xml
eyecatching/static/EyeCatching.jpeg
eyecatching/templates/plot_track.html
eyecatching/templates/upload.html
eyecatching/templates/upload_ok.html