Metadata-Version: 2.1
Name: eyecatching
Version: 0.0.5
Summary: eye catching
Home-page: https://github.com/ShenJimei
Author: Jimei
Author-email: shenjimei33@outlook.com
License: UNKNOWN
Platform: UNKNOWN
Classifier: Programming Language :: Python :: 3
Classifier: License :: OSI Approved :: MIT License
Classifier: Operating System :: OS Independent
Requires-Python: ==3.7.*
